{
  "db_name": "SQLite",
  "query": "SELECT * FROM scenario_iteration ORDER BY start_time DESC LIMIT 1",
  "describe": {
    "columns": [
      {
        "name": "run_id",
        "ordinal": 0,
        "type_info": "Text"
      },
      {
        "name": "scenario_name",
        "ordinal": 1,
        "type_info": "Text"
      },
      {
        "name": "iteration",
        "ordinal": 2,
        "type_info": "Int64"
      },
      {
        "name": "start_time",
        "ordinal": 3,
        "type_info": "Int64"
      },
      {
        "name": "stop_time",
        "ordinal": 4,
        "type_info": "Int64"
      }
    ],
    "parameters": {
      "Right": 0
    },
    "nullable": [
      false,
      false,
      false,
      false,
      false
    ]
  },
  "hash": "db729d680a66ace4952f3bbabc82b2aeaeda1f47c713841effec346a5b930325"
}
